Metadata-Version: 2.1
Name: MiaoPinYin
Version: 0.0.3
Summary: 简单的中文播放
Author: MiaoMiaoLWY
Author-email: 1545113791@qq.com
Classifier: Programming Language :: Python :: 3
Classifier: License :: OSI Approved :: MIT License
Classifier: Operating System :: OS Independent
